pytest_vts/__init__.py
pytest_vts/version.py
pytest_vts/logic/__init__.py
pytest_vts/logic/machine.py
pytest_vts/logic/_compat/__init__.py
pytest_vts/logic/_compat/cookie_parsing_library_errors.py
pytest_vts/vendored/__init__.py
pytest_vts/vendored/_history.py
pytest_vts/vendored/responses.py
pytest_vts/vts/__init__.py
pytest_vts/vts/machine.py
pytest_vts-0.4.8.dist-info/LICENSE
pytest_vts-0.4.8.dist-info/METADATA
pytest_vts-0.4.8.dist-info/WHEEL
pytest_vts-0.4.8.dist-info/entry_points.txt
pytest_vts-0.4.8.dist-info/top_level.txt
pytest_vts-0.4.8.dist-info/RECORD
